elapsedTimerPy/__init__.py
elapsedTimerPy/elapsedTimer.py
elapsedTimerPy-0.0.1.dist-info/METADATA
elapsedTimerPy-0.0.1.dist-info/WHEEL
elapsedTimerPy-0.0.1.dist-info/top_level.txt
elapsedTimerPy-0.0.1.dist-info/RECORD
